sinhaladate/__init__.py
sinhaladate/dates.py
sinhaladate/utils.py
sinhaladate-0.1.0.dist-info/METADATA
sinhaladate-0.1.0.dist-info/WHEEL
sinhaladate-0.1.0.dist-info/top_level.txt
sinhaladate-0.1.0.dist-info/RECORD
