Metadata-Version: 2.4
Name: sinhaladate
Version: 0.1.0
Summary: A Python library for parsing and formatting Sinhala dates and times
Home-page: https://github.com/RavinduPabasara/sinhaladate
Author: Ravindu Pabasara Karunarathna
Author-email: Ravindu Pabasara Karunarathna <karurpabe@gmail.com>
Maintainer-email: Ravindu Pabasara Karunarathna <karurpabe@gmail.com>
Project-URL: Homepage, https://github.com/RavinduPabasara/sinhaladate
Project-URL: Documentation, https://github.com/RavinduPabasara/sinhaladate#readme
Project-URL: Repository, https://github.com/RavinduPabasara/sinhaladate
Project-URL: Bug Tracker, https://github.com/RavinduPabasara/sinhaladate/issues
Keywords: sinhala,date,time,parsing,formatting,sri lanka,natural language
Classifier: Development Status :: 3 - Alpha
Classifier: Intended Audience :: Developers
Classifier: Operating System :: OS Independent
Classifier: Programming Language :: Python :: 3
Classifier: Programming Language :: Python :: 3.7
Classifier: Programming Language :: Python :: 3.8
Classifier: Programming Language :: Python :: 3.9
Classifier: Programming Language :: Python :: 3.10
Classifier: Programming Language :: Python :: 3.11
Classifier: Programming Language :: Python :: 3.12
Classifier: Topic :: Software Development :: Libraries :: Python Modules
Classifier: Topic :: Text Processing :: Linguistic
Requires-Python: >=3.7
Provides-Extra: dev
Requires-Dist: pytest>=6.0; extra == "dev"
Requires-Dist: pytest-cov>=2.0; extra == "dev"
Requires-Dist: black>=21.0; extra == "dev"
Requires-Dist: flake8>=3.8; extra == "dev"
Requires-Dist: mypy>=0.800; extra == "dev"
Dynamic: author
Dynamic: home-page
Dynamic: requires-python
